README.md
pyproject.toml
setup.cfg
setup.py
baseapp_referrals/__init__.py
baseapp_referrals/admin.py
baseapp_referrals/apps.py
baseapp_referrals/models.py
baseapp_referrals/pipeline.py
baseapp_referrals/utils.py
baseapp_referrals.egg-info/PKG-INFO
baseapp_referrals.egg-info/SOURCES.txt
baseapp_referrals.egg-info/dependency_links.txt
baseapp_referrals.egg-info/requires.txt
baseapp_referrals.egg-info/top_level.txt
baseapp_referrals/migrations/0001_initial.py
baseapp_referrals/migrations/__init__.py