Metadata-Version: 2.1
Name: baseapp-referrals
Version: 0.1.0
Summary: BaseApp Referrals
Home-page: https://github.com/silverlogic/baseapp-backend
Author: The SilverLogic
Author-email: dev@tsl.io
License: BSD-3-Clause  # Example license
Platform: UNKNOWN
Requires-Python: >=3.8
